inf581/__init__.py
inf581/lab7.py
inf581-1.0.5.dist-info/AUTHORS
inf581-1.0.5.dist-info/METADATA
inf581-1.0.5.dist-info/WHEEL
inf581-1.0.5.dist-info/top_level.txt
inf581-1.0.5.dist-info/RECORD
